ament_cmake_export_link_flags/_dummy.cpython-313-x86_64-linux-gnu.so
ros_ament_cmake_export_link_flags-2.7.3.data/data/share/ament_cmake_export_link_flags/local_setup.bash
ros_ament_cmake_export_link_flags-2.7.3.data/data/share/ament_cmake_export_link_flags/local_setup.dsv
ros_ament_cmake_export_link_flags-2.7.3.data/data/share/ament_cmake_export_link_flags/local_setup.sh
ros_ament_cmake_export_link_flags-2.7.3.data/data/share/ament_cmake_export_link_flags/local_setup.zsh
ros_ament_cmake_export_link_flags-2.7.3.data/data/share/ament_cmake_export_link_flags/package.dsv
ros_ament_cmake_export_link_flags-2.7.3.data/data/share/ament_cmake_export_link_flags/package.xml
ros_ament_cmake_export_link_flags-2.7.3.data/data/share/ament_cmake_export_link_flags/cmake/ament_cmake_export_link_flags-extras.cmake
ros_ament_cmake_export_link_flags-2.7.3.data/data/share/ament_cmake_export_link_flags/cmake/ament_cmake_export_link_flags-extras.cmake.in
ros_ament_cmake_export_link_flags-2.7.3.data/data/share/ament_cmake_export_link_flags/cmake/ament_cmake_export_link_flagsConfig-version.cmake
ros_ament_cmake_export_link_flags-2.7.3.data/data/share/ament_cmake_export_link_flags/cmake/ament_cmake_export_link_flagsConfig.cmake
ros_ament_cmake_export_link_flags-2.7.3.data/data/share/ament_cmake_export_link_flags/cmake/ament_cmake_export_link_flags_package_hook.cmake
ros_ament_cmake_export_link_flags-2.7.3.data/data/share/ament_cmake_export_link_flags/cmake/ament_export_link_flags.cmake
ros_ament_cmake_export_link_flags-2.7.3.data/data/share/ament_cmake_export_link_flags/environment/ament_prefix_path.dsv
ros_ament_cmake_export_link_flags-2.7.3.data/data/share/ament_cmake_export_link_flags/environment/ament_prefix_path.sh
ros_ament_cmake_export_link_flags-2.7.3.data/data/share/ament_cmake_export_link_flags/environment/path.dsv
ros_ament_cmake_export_link_flags-2.7.3.data/data/share/ament_cmake_export_link_flags/environment/path.sh
ros_ament_cmake_export_link_flags-2.7.3.dist-info/METADATA
ros_ament_cmake_export_link_flags-2.7.3.dist-info/WHEEL
ros_ament_cmake_export_link_flags-2.7.3.dist-info/top_level.txt
ros_ament_cmake_export_link_flags-2.7.3.dist-info/RECORD
