Metadata-Version: 2.4
Name: ros-ament-cmake-export-link-flags
Version: 2.7.3
Summary: Wheel for the ament_cmake_export_link_flags (ros-ament-cmake-export-link-flags) ROS 2 package.
Dynamic: description
Dynamic: description-content-type
Dynamic: summary
